Workbook
Name aporte: APP!$G$32
Name dividendos_mensais: APP!$G$36
Name patrimonio_acumulado: APP!$G$35
Name qtd_anos: APP!$G$33
Name rendimento_carteira: APP!$G$27
Name salario: APP!$G$26
Name sugestao_investimento: APP!$G$28
Name taxa_mensal: APP!$G$34

Sheet APP
B25: CONFIGURAÇÕES
B26: Salário | G26: 3000
B27: Rendimento carteira | G27: 0.008
B28: Sugestão de investimento | G28: =G26*30% -> 900
B31: INVESTIMENTO MENSAL
B32: Quanto investir por mês? | G32: 600
A33: 6 | B33: Por quantos anos? | G33: 5
A34: 12 | B34: Taxa de rendimento mensal? | G34: 0.005
A35: 15 | B35: Patrimônio acumulado? | G35: =FV(taxa_mensal,qtd_anos*12,aporte*-1) -> 41862.018
A36: 40 | B36: Dividendos mensais? | G36: =patrimonio_acumulado*rendimento_carteira -> 334.89615
B39: CENÁRIOS | G39: Dividendo
B40: Quanto em 6 anos? | F40: =FV($G$34,$A33*12,$G$32*-1) -> 51845.313 | G40: =F40*rendimento_carteira -> 414.76251
B41: Quanto em 12 anos? | F41: =FV($G$34,$A34*12,$G$32*-1) -> 126090.1 | G41: =F41*rendimento_carteira -> 1008.7208
B42: Quanto em 15 anos? | F42: =FV($G$34,$A35*12,$G$32*-1) -> 174491.23 | G42: =F42*rendimento_carteira -> 1395.9298
B43: Quanto em 40 anos? | F43: =FV($G$34,$A36*12,$G$32*-1) -> 1194894.4 | G43: =F43*rendimento_carteira -> 9559.1555
B46: Perfil | F46: CONSERVADOR
B47: Valor a ser investido por mês | F47: =aporte -> 600
B50: TIPO DE FII | F50: PERCENTUAL SUGERIDO | G50: VALORES
B51: PAPEL | F51: =VLOOKUP($F$46&"-"&B51,TABELA_APOIO!$B:$E,4,FALSE) -> 0.2 | G51: =F51*$F$47 -> 120
B52: TIJOLO | F52: =VLOOKUP($F$46&"-"&B52,TABELA_APOIO!$B:$E,4,FALSE) -> 0.6 | G52: =F52*$F$47 -> 360
B53: HÍBRIDOS | F53: =VLOOKUP($F$46&"-"&B53,TABELA_APOIO!$B:$E,4,FALSE) -> 0.05 | G53: =F53*$F$47 -> 30
B54: FOFs | F54: =VLOOKUP($F$46&"-"&B54,TABELA_APOIO!$B:$E,4,FALSE) -> 0.05 | G54: =F54*$F$47 -> 30
B55: DESENVOLVIMENTO | F55: =VLOOKUP($F$46&"-"&B55,TABELA_APOIO!$B:$E,4,FALSE) -> 0.05 | G55: =F55*$F$47 -> 30
B56: HOTELARIAS | F56: =VLOOKUP($F$46&"-"&B56,TABELA_APOIO!$B:$E,4,FALSE) -> 0.05 | G56: =F56*$F$47 -> 30
G57: =SUM(G51:G56) -> 600

Sheet TABELA_APOIO
B2: CHAVE | C2: PERFIL | D2: TIPO DE FII | E2: %
B3: =C3&"-"&D3 -> CONSERVADOR-PAPEL | C3: CONSERVADOR | D3: PAPEL | E3: 0.2
B4: =C4&"-"&D4 -> CONSERVADOR-TIJOLO | C4: CONSERVADOR | D4: TIJOLO | E4: 0.6
B5: =C5&"-"&D5 -> CONSERVADOR-HÍBRIDOS | C5: CONSERVADOR | D5: HÍBRIDOS | E5: 0.05
B6: =C6&"-"&D6 -> CONSERVADOR-FOFs | C6: CONSERVADOR | D6: FOFs | E6: 0.05
B7: =C7&"-"&D7 -> CONSERVADOR-DESENVOLVIMENTO | C7: CONSERVADOR | D7: DESENVOLVIMENTO | E7: 0.05
B8: =C8&"-"&D8 -> CONSERVADOR-HOTELARIAS | C8: CONSERVADOR | D8: HOTELARIAS | E8: 0.05
B9: =C9&"-"&D9 -> MODERADO-PAPEL | C9: MODERADO | D9: PAPEL | E9: 0.4
B10: =C10&"-"&D10 -> MODERADO-TIJOLO | C10: MODERADO | D10: TIJOLO | E10: 0.4
B11: =C11&"-"&D11 -> MODERADO-HÍBRIDOS | C11: MODERADO | D11: HÍBRIDOS | E11: 0.05
B12: =C12&"-"&D12 -> MODERADO-FOFs | C12: MODERADO | D12: FOFs | E12: 0.05
B13: =C13&"-"&D13 -> MODERADO-DESENVOLVIMENTO | C13: MODERADO | D13: DESENVOLVIMENTO | E13: 0.05
B14: =C14&"-"&D14 -> MODERADO-HOTELARIAS | C14: MODERADO | D14: HOTELARIAS | E14: 0.05
... B20: =C20&"-"&D20 -> AGRESSIVO-HOTELARIAS | C20: AGRESSIVO | D20: HOTELARIAS | E20: 0.05
